MANIFEST.in
README.rst
setup.py
distext.egg-info/PKG-INFO
distext.egg-info/SOURCES.txt
distext.egg-info/dependency_links.txt
distext.egg-info/namespace_packages.txt
distext.egg-info/not-zip-safe
distext.egg-info/requires.txt
distext.egg-info/top_level.txt
silveregg/__init__.py
silveregg/distext/__gen_version.py
silveregg/distext/__init__.py
silveregg/distext/core.py
silveregg/distext/dist.py
silveregg/distext/hgutils.py
silveregg/distext/utils.py
silveregg/distext/command/__init__.py
silveregg/distext/command/bdist_egg.py
silveregg/distext/command/build.py
silveregg/distext/command/build_init_scripts.py
silveregg/distext/command/build_py.py
silveregg/distext/command/install.py
silveregg/distext/command/sdist.py