Metadata-Version: 1.0
Name: distext
Version: 0.0.4
Summary: Silveregg distutils extensions
Home-page: UNKNOWN
Author: Silveregg Technologies Ltd.
Author-email: dev@silveregg.co.jp
License: BSD
Platform: UNKNOWN
